Workbook
Name Income: #REF!

Sheet 速卖通-mini管报-26年X月
F1: 当月汇率
A2: 事业部 | B2: Aliexpress(速卖通) | F2: 45597 | G2: 7.1898 | H2: 事业部 | I2: Aliexpress | L2: 事业部 | M2: Aliexpress | O2: 事业部 | P2: Aliexpress | R2: 事业部 | S2: Aliexpress | U2: 事业部 | V2: Aliexpress | X2: 事业部 | Y2: Aliexpress | AA2: 事业部 | AB2: Aliexpress | AD2: 事业部 | AE2: Aliexpress | AG2: 事业部 | AH2: Aliexpress | AJ2: 事业部 | AK2: Aliexpress | AM2: 事业部 | AN2: Aliexpress | AP2: 事业部 | AQ2: Aliexpress | AS2: 事业部 | AT2: Aliexpress | AV2: 事业部 | AW2: Aliexpress | AY2: 事业部 | AZ2: Aliexpress(速卖通) | BB2: 事业部 | BC2: Aliexpress(速卖通)
A3: ="时间：2026年"&MONTH(速卖通退款!$O$2)&"月" -> 时间：2026年1月 | B3: 绝对值 | C3: 费比 | D3: 备注 | F3: 45627 | G3: 7.18805 | H3: 时间：2024年12月 | I3: 绝对值 | J3: 费比 | K3: 备注 | L3: 时间：2025年1月 | M3: 绝对值 | N3: 费比 | O3: 时间：2025年2月 | P3: 绝对值 | Q3: 费比 | R3: 时间：2025年3月 | S3: 绝对值 | T3: 费比 | U3: 时间：2025年4月 | V3: 绝对值 | W3: 费比 | X3: 时间：2025年5月 | Y3: 绝对值 | Z3: 费比 | AA3: 时间：2025年6月 | AB3: 绝对值 | AC3: 费比 | AD3: 时间：2025年7月 | AE3: 绝对值 | AF3: 费比 | AG3: 时间：2025年8月 | AH3: 绝对值 | AI3: 费比 | AJ3: 时间：2025年9月 | AK3: 绝对值 | AL3: 费比 | AM3: 时间：2025年10月 | AN3: 绝对值 | AO3: 费比 | AP3: 时间：2025年11月 | AQ3: 绝对值 | AR3: 费比 | AS3: 时间：2025年12月 | AT3: 绝对值 | AU3: 费比 | AV3: 时间：2026年1月 | AW3: 绝对值 | AX3: 费比 | AY3: 时间：2026年2月 | AZ3: 绝对值 | BA3: 费比 | BB3: 时间：2026年3月 | BC3: 绝对值 | BD3: 费比
A4: 前台GMV（含税） | F4: 45658 | G4: 7.1791 | H4: 前台GMV（含税） | L4: 前台GMV（含税） | O4: 前台GMV（含税） | R4: 前台GMV（含税） | U4: 前台GMV（含税） | X4: 前台GMV（含税） | AA4: 前台GMV（含税） | AD4: 前台GMV（含税） | AG4: 前台GMV（含税） | AJ4: 前台GMV（含税） | AM4: 前台GMV（含税） | AP4: 前台GMV（含税） | AS4: 前台GMV（含税） | AV4: 前台GMV（含税） | AY4: 前台GMV（含税） | BB4: 前台GMV（含税）
A5: 销售收入 | B5: =B6+B7+B8 -> 0 | F5: 45689 | G5: 7.1718 | H5: 销售收入 | I5: 413175.87 | L5: 销售收入 | M5: 306530.98 | O5: 销售收入 | P5: 225454.64 | R5: 销售收入 | S5: 507837.03 | U5: 销售收入 | V5: 300043.36 | X5: 销售收入 | Y5: 331799.56 | AA5: 销售收入 | AB5: 493946.56 | AD5: 销售收入 | AE5: 334717.75 | AG5: 销售收入 | AH5: 550842.29 | AJ5: 销售收入 | AK5: 418336.43 | AM5: 销售收入 | AN5: 622562.69 | AP5: 销售收入 | AQ5: 1224573.8 | AS5: 销售收入 | AT5: 291191.85 | AV5: 销售收入 | AW5: 228230.45 | AY5: 销售收入 | AZ5: 271294.95 | BB5: 销售收入 | BC5: 410242.11
A6: 平台收入 | B6: ='收入成本汇总表-最终'!F1+'收入成本汇总表-最终'!I1 -> 0 | F6: 45717 | G6: 7.176 | H6: 平台收入 | I6: 420190.04 | L6: 平台收入 | M6: 316381.63 | O6: 平台收入 | P6: 226882.19 | R6: 平台收入 | S6: 509460.41 | U6: 平台收入 | V6: 300644.65 | X6: 平台收入 | Y6: 337076.43 | AA6: 平台收入 | AB6: 497915.01 | AD6: 平台收入 | AE6: 342861.17 | AG6: 平台收入 | AH6: 564156.24 | AJ6: 平台收入 | AK6: 444664.54 | AM6: 平台收入 | AN6: 636622.49 | AP6: 平台收入 | AQ6: 1225055 | AS6: 平台收入 | AT6: 300788.31 | AV6: 平台收入 | AW6: 241371.65 | AY6: 平台收入 | AZ6: 280429.06 | BB6: 平台收入 | BC6: 403928.48
A7: 平台退款 | B7: ='收入成本汇总表-最终'!J1 -> 0 | F7: 45748 | G7: 7.1898 | H7: 平台退款 | I7: -8332.747 | L7: 平台退款 | M7: -10731.893 | O7: 平台退款 | P7: -6621.5795 | R7: 平台退款 | S7: -3271.7537 | U7: 平台退款 | V7: -3644.1501 | X7: 平台退款 | Y7: -10637.516 | AA7: 平台退款 | AB7: -7252.8119 | AD7: 平台退款 | AE7: -10320.79 | AG7: 平台退款 | AH7: -14746.103 | AJ7: 平台退款 | AK7: -27222.825 | AM7: 平台退款 | AN7: -18580.487 | AP7: 平台退款 | AQ7: -17889.663 | AS7: 平台退款 | AT7: -21536.967 | AV7: 平台退款 | AW7: -15351.331 | AY7: 平台退款 | AZ7: -9432.6897 | BB7: 平台退款 | BC7: -6584.7345
A8: 其他收入 | B8: ='收入成本汇总表-最终'!K1 -> 0 | F8: 45778 | G8: 7.1931 | H8: 其他收入 | I8: 1318.5759 | K8: 物流赔款 | L8: 其他收入 | M8: 881.24012 | O8: 其他收入 | P8: 5194.0327 | R8: 其他收入 | S8: 1648.38 | U8: 其他收入 | V8: 3042.8641 | X8: 其他收入 | Y8: 5360.6413 | AA8: 其他收入 | AB8: 3284.3603 | AD8: 其他收入 | AE8: 2177.3661 | AG8: 其他收入 | AH8: 1432.1524 | AJ8: 其他收入 | AK8: 894.71554 | AM8: 其他收入 | AN8: 4520.6832 | AP8: 其他收入 | AQ8: 17408.471 | AS8: 其他收入 | AT8: 11940.504 | AV8: 其他收入 | AW8: 2210.1331 | AY8: 其他收入 | AZ8: 298.57845 | BB8: 其他收入 | BC8: 12898.37
A9: 营业成本 | B9: =B10+B11+B12 -> 0 | C9: =B9/B$5 -> #DIV/0! | F9: 45809 | G9: 7.1717 | H9: 营业成本 | I9: 204919.39 | J9: 0.49596166 | L9: 营业成本 | M9: 147496.13 | N9: 0.48117854 | O9: 营业成本 | P9: 97620.49 | Q9: 0.43299393 | R9: 营业成本 | S9: 251343.33 | T9: 0.49282369 | U9: 营业成本 | V9: 139867 | W9: 0.49282369 | X9: 营业成本 | Y9: 149160.71 | Z9: 0.49282369 | AA9: 营业成本 | AB9: 234150.12 | AC9: 0.47403938 | AD9: 营业成本 | AE9: 163251.44 | AF9: 0.48772866 | AG9: 营业成本 | AH9: 259191.85 | AI9: 0.47053731 | AJ9: 营业成本 | AK9: 194058.83 | AL9: 0.46388222 | AM9: 营业成本 | AN9: 252842.15 | AO9: 0.40613123 | AP9: 营业成本 | AQ9: 531698.91 | AR9: 0.43419099 | AS9: 营业成本 | AT9: 141709.48 | AU9: 0.48665332 | AV9: 营业成本 | AW9: 116232.02 | AX9: 0.50927482 | AY9: 营业成本 | AZ9: 135915.72 | BA9: 0.50098876 | BB9: 营业成本 | BC9: 195716.3 | BD9: 0.47707511
A10: 采购成本 | B10: ='收入成本汇总表-最终'!L1 -> 0 | C10: =B10/B$5 -> #DIV/0! | F10: 45839 | G10: 7.154 | H10: 采购成本 | I10: 204919.39 | J10: =I10/I5 -> 0.49596166 | L10: 采购成本 | M10: 147496.13 | N10: 0.48117854 | O10: 采购成本 | P10: 97620.49 | Q10: 0.43299393 | R10: 采购成本 | S10: 250993.33 | T10: 0.49213742 | U10: 采购成本 | V10: 139412.6 | W10: 0.49213742 | X10: 采购成本 | Y10: 148360.71 | Z10: 0.49213742 | AA10: 采购成本 | AB10: 233350.12 | AC10: 0.47241977 | AD10: 采购成本 | AE10: 162051.44 | AF10: 0.48414355 | AG10: 采购成本 | AH10: 258791.85 | AI10: 0.46981115 | AJ10: 采购成本 | AK10: 193198.83 | AL10: 0.46182646 | AM10: 采购成本 | AN10: 251642.15 | AO10: 0.40420371 | AP10: 采购成本 | AQ10: 530498.91 | AR10: 0.43321106 | AS10: 采购成本 | AT10: 140509.48 | AU10: 0.48253233 | AV10: 采购成本 | AW10: 115432.02 | AX10: 0.50576959 | AY10: 采购成本 | AZ10: 135095.72 | BA10: 0.49796622 | BB10: 采购成本 | BC10: 194916.3 | BD10: 0.47512504
A11: 头程成本 | B11: ='收入成本汇总表-最终'!M1 -> 0 | C11: =B11/B$5 -> #DIV/0! | F11: 45870 | G11: 7.1262 | H11: 头程成本 | L11: 头程成本 | O11: 头程成本 | R11: 头程成本 | S11: 350 | U11: 头程成本 | V11: 454.4 | X11: 头程成本 | Y11: 800 | AA11: 头程成本 | AB11: 800 | AD11: 头程成本 | AE11: 1200 | AF11: 0.0035851101 | AG11: 头程成本 | AH11: 400 | AI11: 0.00072616066 | AJ11: 头程成本 | AK11: 860 | AL11: 0.0020557617 | AM11: 头程成本 | AN11: 1200 | AO11: 0.0019275167 | AP11: 头程成本 | AQ11: 1200 | AR11: 0.00097993278 | AS11: 头程成本 | AT11: 1200 | AU11: 0.0041209945 | AV11: 头程成本 | AW11: 800 | AX11: 0.003505229 | AY11: 头程成本 | AZ11: 820 | BA11: 0.0030225406 | BB11: 头程成本 | BC11: 800 | BD11: 0.001950068
A12: 关税 | B12: 0 | F12: 45901 | G12: 7.1043 | H12: 关税 | L12: 关税 | O12: 关税 | R12: 关税 | U12: 关税 | X12: 关税 | AA12: 关税 | AD12: 关税 | AG12: 关税 | AJ12: 关税 | AM12: 关税 | AP12: 关税 | AS12: 关税 | AV12: 关税 | AY12: 关税 | BB12: 关税 | BC12: 0
A13: 营销费用 | B13: =B14+B15+B16+B17 -> 0 | C13: =B13/B$5 -> #DIV/0! | F13: 45931 | G13: 7.0968 | H13: 营销费用 | I13: 14029.976 | J13: =I13/I5 -> 0.033956427 | L13: 营销费用 | M13: 15122.355 | N13: 0.049333856 | O13: 营销费用 | P13: 11970.116 | Q13: 0.053093236 | R13: 营销费用 | S13: 24441.736 | T13: 0.047924353 | U13: 营销费用 | V13: 16615.479 | W13: 0.047924353 | X13: 营销费用 | Y13: 16528.455 | Z13: 0.047924353 | AA13: 营销费用 | AB13: 17914.115 | AC13: 0.036267315 | AD13: 营销费用 | AE13: 17783.481 | AF13: 0.05312978 | AG13: 营销费用 | AH13: 20993.029 | AI13: 0.038110779 | AJ13: 营销费用 | AK13: 18619.675 | AL13: 0.044508855 | AM13: 营销费用 | AN13: 23285.762 | AO13: 0.03740308 | AP13: 营销费用 | AQ13: 51753.039 | AR13: 0.042262083 | AS13: 营销费用 | AT13: 18921.761 | AU13: 0.064980393 | AV13: 营销费用 | AW13: 16178.475 | AX13: 0.070886575 | AY13: 营销费用 | AZ13: 15109.15 | BA13: 0.055692707 | BB13: 营销费用 | BC13: 35223.906 | BD13: 0.085861264
A14: 站内推广费 | B14: ='收入成本汇总表-最终'!T1+'收入成本汇总表-最终'!U1+'收入成本汇总表-最终'!W1+'收入成本汇总表-最终'!X1 -> 0 | C14: =B14/B$5 -> #DIV/0! | F14: 45962 | G14: 7.0835 | H14: 站内推广费 | I14: 14029.976 | J14: =I14/I5 -> 0.033956427 | K14: USD287.67 | L14: 站内推广费 | M14: 15122.355 | N14: 0.049333856 | O14: 站内推广费 | P14: 11970.116 | Q14: 0.053093236 | R14: 站内推广费 | S14: 24441.736 | T14: 0.047924353 | U14: 站内推广费 | V14: 16615.479 | W14: 0.047924353 | X14: 站内推广费 | Y14: 16528.455 | Z14: 0.047924353 | AA14: 站内推广费 | AB14: 17914.115 | AC14: 0.036267315 | AD14: 站内推广费 | AE14: 17783.481 | AF14: 0.05312978 | AG14: 站内推广费 | AH14: 20993.029 | AI14: 0.038110779 | AJ14: 站内推广费 | AK14: 18619.675 | AL14: 0.044508855 | AM14: 站内推广费 | AN14: 23285.762 | AO14: 0.03740308 | AP14: 站内推广费 | AQ14: 51753.039 | AR14: 0.042262083 | AS14: 站内推广费 | AT14: 18921.761 | AU14: 0.064980393 | AV14: 站内推广费 | AW14: 16178.475 | AX14: 0.070886575 | AY14: 站内推广费 | AZ14: 15109.15 | BA14: 0.055692707 | BB14: 站内推广费 | BC14: 35223.906 | BD14: 0.085861264
A15: 站外推广费 | B15: 0 | F15: 45992 | G15: 7.0539 | H15: 站外推广费 | I15: 0 | L15: 站外推广费 | M15: 0 | O15: 站外推广费 | P15: 0 | R15: 站外推广费 | S15: 0 | U15: 站外推广费 | V15: 0 | X15: 站外推广费 | Y15: 0 | AA15: 站外推广费 | AB15: 0 | AD15: 站外推广费 | AE15: 0 | AG15: 站外推广费 | AH15: 0 | AJ15: 站外推广费 | AK15: 0 | AM15: 站外推广费 | AN15: 0 | AP15: 站外推广费 | AQ15: 0 | AS15: 站外推广费 | AT15: 0 | AV15: 站外推广费 | AW15: 0 | AY15: 站外推广费 | AZ15: 0 | BB15: 站外推广费 | BC15: 0
A16: 市场费用 | B16: 0 | F16: 46023 | G16: 6.9983 | H16: 市场费用 | I16: 0 | L16: 市场费用 | M16: 0 | O16: 市场费用 | P16: 0 | R16: 市场费用 | S16: 0 | U16: 市场费用 | V16: 0 | X16: 市场费用 | Y16: 0 | AA16: 市场费用 | AB16: 0 | AD16: 市场费用 | AE16: 0 | AG16: 市场费用 | AH16: 0 | AJ16: 市场费用 | AK16: 0 | AM16: 市场费用 | AN16: 0 | AP16: 市场费用 | AQ16: 0 | AS16: 市场费用 | AT16: 0 | AV16: 市场费用 | AW16: 0 | AY16: 市场费用 | AZ16: 0 | BB16: 市场费用 | BC16: 0
A17: 品牌费用 | B17: 0 | F17: 46054 | G17: 6.9453 | H17: 品牌费用 | I17: 0 | L17: 品牌费用 | M17: 0 | O17: 品牌费用 | P17: 0 | R17: 品牌费用 | S17: 0 | U17: 品牌费用 | V17: 0 | X17: 品牌费用 | Y17: 0 | AA17: 品牌费用 | AB17: 0 | AD17: 品牌费用 | AE17: 0 | AG17: 品牌费用 | AH17: 0 | AJ17: 品牌费用 | AK17: 0 | AM17: 品牌费用 | AN17: 0 | AP17: 品牌费用 | AQ17: 0 | AS17: 品牌费用 | AT17: 0 | AV17: 品牌费用 | AW17: 0 | AY17: 品牌费用 | AZ17: 0 | BB17: 品牌费用 | BC17: 0
A18: 物流费用 | B18: =B19+B22 -> 0 | C18: =B18/B$5 -> #DIV/0! | F18: 46082 | G18: 6.9211 | H18: 物流费用 | I18: 61308.86 | J18: =I18/I5 -> 0.14838442 | L18: 物流费用 | M18: 42932.94 | N18: 0.14006069 | O18: 物流费用 | P18: 28990.4 | Q18: 0.1285864 | R18: 物流费用 | S18: 72364.8 | T18: 0.13209467 | U18: 物流费用 | V18: 40925.01 | W18: 0.13209467 | X18: 物流费用 | Y18: 44599.2 | Z18: 0.13209467 | AA18: 物流费用 | AB18: 69274.875 | AC18: 0.14024771 | AD18: 物流费用 | AE18: 48172.37 | AF18: 0.14391938 | AG18: 物流费用 | AH18: 76601.85 | AI18: 0.13906312 | AJ18: 物流费用 | AK18: 59871.48 | AL18: 0.14311802 | AM18: 物流费用 | AN18: 82579.82 | AO18: 0.13264499 | AP18: 物流费用 | AQ18: 162261.59 | AR18: 0.13250454 | AS18: 物流费用 | AT18: 44523.11 | AU18: 0.15289958 | AV18: 物流费用 | AW18: 34455.85 | AX18: 0.15096956 | AY18: 物流费用 | AZ18: 38354.524 | BA18: 0.14137574 | BB18: 物流费用 | BC18: 56651.08 | BD18: 0.13809182
A19: 尾程费用 | B19: =B20+B21 -> 0 | C19: =B19/B$5 -> #DIV/0! | H19: 尾程费用 | I19: 60412.7 | J19: =I19/I5 -> 0.14621546 | L19: 尾程费用 | M19: 42070.01 | N19: 0.13724554 | O19: 尾程费用 | P19: 28298.63 | Q19: 0.12551806 | R19: 尾程费用 | S19: 72145.83 | T19: 0.13166443 | U19: 尾程费用 | V19: 40525.01 | W19: 0.13166443 | X19: 尾程费用 | Y19: 44148.03 | Z19: 0.13166443 | AA19: 尾程费用 | AB19: 68967.095 | AC19: 0.13962461 | AD19: 尾程费用 | AE19: 47727.91 | AF19: 0.14259151 | AG19: 尾程费用 | AH19: 75876.91 | AI19: 0.13774707 | AJ19: 尾程费用 | AK19: 59512.07 | AL19: 0.14225888 | AM19: 尾程费用 | AN19: 82172.83 | AO19: 0.13199125 | AP19: 尾程费用 | AQ19: 162018.66 | AR19: 0.13230616 | AS19: 尾程费用 | AT19: 44107.73 | AU19: 0.15147309 | AV19: 尾程费用 | AW19: 34161.02 | AX19: 0.14967775 | AY19: 尾程费用 | AZ19: 38239.224 | BA19: 0.14095074 | BB19: 尾程费用 | BC19: 55996.88 | BD19: 0.13649715
A20: 平台仓尾程 | B20: ='收入成本汇总表-最终'!O1 -> 0 | C20: =B20/B$5 -> #DIV/0! | H20: 平台仓尾程 | I20: 60412.7 | J20: =I20/I5 -> 0.14621546 | L20: 平台仓尾程 | M20: 42070.01 | N20: 0.13724554 | O20: 平台仓尾程 | P20: 28298.63 | Q20: 0.12551806 | R20: 平台仓尾程 | S20: 72145.83 | T20: 0.13166443 | U20: 平台仓尾程 | V20: 40525.01 | W20: 0.13166443 | X20: 平台仓尾程 | Y20: 44148.03 | Z20: 0.13166443 | AA20: 平台仓尾程 | AB20: 68967.095 | AC20: 0.13962461 | AD20: 平台仓尾程 | AE20: 47727.91 | AF20: 0.14259151 | AG20: 平台仓尾程 | AH20: 75876.91 | AI20: 0.13774707 | AJ20: 平台仓尾程 | AK20: 59512.07 | AL20: 0.14225888 | AM20: 平台仓尾程 | AN20: 82172.83 | AO20: 0.13199125 | AP20: 平台仓尾程 | AQ20: 162018.66 | AR20: 0.13230616 | AS20: 平台仓尾程 | AT20: 44107.73 | AU20: 0.15147309 | AV20: 平台仓尾程 | AW20: 34161.02 | AX20: 0.14967775 | AY20: 平台仓尾程 | AZ20: 38239.224 | BA20: 0.14095074 | BB20: 平台仓尾程 | BC20: 55996.88 | BD20: 0.13649715
A21: 海外仓尾程 | H21: 海外仓尾程 | L21: 海外仓尾程 | O21: 海外仓尾程 | R21: 海外仓尾程 | U21: 海外仓尾程 | X21: 海外仓尾程 | AA21: 海外仓尾程 | AD21: 海外仓尾程 | AG21: 海外仓尾程 | AJ21: 海外仓尾程 | AM21: 海外仓尾程 | AP21: 海外仓尾程 | AS21: 海外仓尾程 | AV21: 海外仓尾程 | AY21: 海外仓尾程 | BB21: 海外仓尾程
A22: 仓租费用 | B22: =B23+B24 -> 0 | C22: =B22/B$5 -> #DIV/0! | H22: 仓租费用 | I22: 896.16 | J22: =I22/I5 -> 0.0021689553 | L22: 仓租费用 | M22: 862.93 | N22: 0.0028151478 | O22: 仓租费用 | P22: 691.77 | Q22: 0.0030683334 | R22: 仓租费用 | S22: 218.97 | T22: 0.00042934739 | U22: 仓租费用 | V22: 400 | W22: 0.00042934739 | X22: 仓租费用 | Y22: 451.17 | Z22: 0.00042934739 | AA22: 仓租费用 | AB22: 307.78 | AC22: 0.00062310385 | AD22: 仓租费用 | AE22: 444.46 | AF22: 0.001327865 | AG22: 仓租费用 | AH22: 724.94 | AI22: 0.0013160573 | AJ22: 仓租费用 | AK22: 359.41 | AL22: 0.00085914106 | AM22: 仓租费用 | AN22: 406.99 | AO22: 0.00065373337 | AP22: 仓租费用 | AQ22: 242.93 | AR22: 0.00019837922 | AS22: 仓租费用 | AT22: 415.38 | AU22: 0.0014264822 | AV22: 仓租费用 | AW22: 294.83 | AX22: 0.0012918084 | AY22: 仓租费用 | AZ22: 115.3 | BA22: 0.0004249987 | BB22: 仓租费用 | BC22: 654.2 | BD22: 0.0015946681
A23: 平台仓仓租 | B23: ='收入成本汇总表-最终'!R1 -> 0 | C23: =B23/B$5 -> #DIV/0! | H23: 平台仓仓租 | I23: 896.16 | J23: =I23/I5 -> 0.0021689553 | L23: 平台仓仓租 | M23: 862.93 | N23: 0.0028151478 | O23: 平台仓仓租 | P23: 691.77 | Q23: 0.0030683334 | R23: 平台仓仓租 | S23: 218.97 | T23: 0.00042934739 | U23: 平台仓仓租 | V23: 400 | W23: 0.00042934739 | X23: 平台仓仓租 | Y23: 451.17 | Z23: 0.00042934739 | AA23: 平台仓仓租 | AB23: 307.78 | AC23: 0.00062310385 | AD23: 平台仓仓租 | AE23: 444.46 | AF23: 0.001327865 | AG23: 平台仓仓租 | AH23: 724.94 | AI23: 0.0013160573 | AJ23: 平台仓仓租 | AK23: 359.41 | AL23: 0.00085914106 | AM23: 平台仓仓租 | AN23: 406.99 | AO23: 0.00065373337 | AP23: 平台仓仓租 | AQ23: 242.93 | AR23: 0.00019837922 | AS23: 平台仓仓租 | AT23: 415.38 | AU23: 0.0014264822 | AV23: 平台仓仓租 | AW23: 294.83 | AX23: 0.0012918084 | AY23: 平台仓仓租 | AZ23: 115.3 | BA23: 0.0004249987 | BB23: 平台仓仓租 | BC23: 654.2 | BD23: 0.0015946681
A24: 海外仓仓租 | H24: 海外仓仓租 | L24: 海外仓仓租 | O24: 海外仓仓租 | R24: 海外仓仓租 | U24: 海外仓仓租 | X24: 海外仓仓租 | AA24: 海外仓仓租 | AD24: 海外仓仓租 | AG24: 海外仓仓租 | AJ24: 海外仓仓租 | AM24: 海外仓仓租 | AP24: 海外仓仓租 | AS24: 海外仓仓租 | AV24: 海外仓仓租 | AY24: 海外仓仓租 | BB24: 海外仓仓租
A25: 其他物流费用 | H25: 其他物流费用 | L25: 其他物流费用 | O25: 其他物流费用 | R25: 其他物流费用 | U25: 其他物流费用 | X25: 其他物流费用 | AA25: 其他物流费用 | AD25: 其他物流费用 | AG25: 其他物流费用 | AJ25: 其他物流费用 | AM25: 其他物流费用 | AP25: 其他物流费用 | AS25: 其他物流费用 | AV25: 其他物流费用 | AY25: 其他物流费用 | BB25: 其他物流费用
A26: 平台费用 | B26: =SUM(B27:B31) -> 0 | C26: =B26/B$5 -> #DIV/0! | H26: 平台费用 | I26: 36483.864 | J26: =I26/I5 -> 0.088301052 | L26: 平台费用 | M26: 27639.417 | N26: 0.090168431 | O26: 平台费用 | P26: 19913.355 | Q26: 0.088325326 | R26: 平台费用 | S26: 45851.437 | T26: 0.089995587 | U26: 平台费用 | V26: 27058.019 | W26: 0.089995587 | X26: 平台费用 | Y26: 30336.879 | Z26: 0.089995587 | AA26: 平台费用 | AB26: 44440.99 | AC26: 0.089971252 | AD26: 平台费用 | AE26: 30269.563 | AF26: 0.090433097 | AG26: 平台费用 | AH26: 63794.225 | AI26: 0.11581214 | AJ26: 平台费用 | AK26: 55160.361 | AL26: 0.13185646 | AM26: 平台费用 | AN26: 79294.303 | AO26: 0.12736758 | AP26: 平台费用 | AQ26: 153111.6 | AR26: 0.12503256 | AS26: 平台费用 | AT26: 37270.118 | AU26: 0.12799163 | AV26: 平台费用 | AW26: 27582.212 | AX26: 0.12085246 | AY26: 平台费用 | AZ26: 32226.78 | BA26: 0.11878872 | BB26: 平台费用 | BC26: 46581.639 | BD26: 0.1135467
A27: 平台佣金 | H27: 平台佣金 | L27: 平台佣金 | O27: 平台佣金 | R27: 平台佣金 | U27: 平台佣金 | X27: 平台佣金 | AA27: 平台佣金 | AD27: 平台佣金 | AG27: 平台佣金 | AJ27: 平台佣金 | AM27: 平台佣金 | AP27: 平台佣金 | AS27: 平台佣金 | AV27: 平台佣金 | AY27: 平台佣金 | BB27: 平台佣金
A28: 平台保险费 | B28: ='收入成本汇总表-最终'!V1 -> 0 | C28: =B28/B$5 -> #DIV/0! | H28: 平台保险费 | I28: 4201.9004 | J28: 0.010169762 | L28: 平台保险费 | M28: 3163.8163 | N28: 0.010321359 | O28: 平台保险费 | P28: 2268.8219 | Q28: 0.010063319 | R28: 平台保险费 | S28: 5094.6041 | T28: 0.0099995097 | U28: 平台保险费 | V28: 3006.4465 | W28: 0.0099995097 | X28: 平台保险费 | Y28: 3370.7643 | Z28: 0.0099995097 | AA28: 平台保险费 | AB28: 5002.3375 | AC28: 0.010127285 | AD28: 平台保险费 | AE28: 3453.1628 | AF28: 0.010316641 | AG28: 平台保险费 | AH28: 5668.5194 | AI28: 0.010290639 | AJ28: 平台保险费 | AK28: 4465.969 | AL28: 0.010675544 | AM28: 平台保险费 | AN28: 6380.4362 | AO28: 0.010248665 | AP28: 平台保险费 | AQ28: 12286.255 | AR28: 0.010033087 | AS28: 平台保险费 | AT28: 3024.0909 | AU28: 0.010385218 | AV28: 平台保险费 | AW28: 0 | AX28: 0 | AY28: 平台保险费 | AZ28: 0 | BB28: 平台保险费 | BC28: 0 | BD28: 0
A29: 月租费 | B29: 0 | H29: 月租费 | I29: 0 | L29: 月租费 | M29: 0 | O29: 月租费 | P29: 0 | R29: 月租费 | S29: 0 | U29: 月租费 | V29: 0 | X29: 月租费 | Y29: 0 | AA29: 月租费 | AB29: 0 | AD29: 月租费 | AE29: 0 | AG29: 月租费 | AH29: 0 | AJ29: 月租费 | AK29: 0 | AM29: 月租费 | AN29: 0 | AP29: 月租费 | AQ29: 0 | AS29: 月租费 | AT29: 0 | AV29: 月租费 | AW29: 0 | AY29: 月租费 | AZ29: 0 | BB29: 月租费 | BC29: 0
A30: 交易手续费 | B30: ='收入成本汇总表-最终'!S1 -> 0 | C30: =B30/B$5 -> #DIV/0! | H30: 交易手续费 | I30: 32281.964 | J30: =I30/I5 -> 0.07813129 | L30: 交易手续费 | M30: 24475.601 | N30: 0.079847072 | O30: 交易手续费 | P30: 17644.533 | Q30: 0.078262008 | R30: 交易手续费 | S30: 40756.833 | T30: 0.079996077 | U30: 交易手续费 | V30: 24051.572 | W30: 0.079996077 | X30: 交易手续费 | Y30: 26966.115 | Z30: 0.079996077 | AA30: 交易手续费 | AB30: 39438.653 | AC30: 0.079843967 | AD30: 交易手续费 | AE30: 26816.4 | AF30: 0.080116456 | AG30: 交易手续费 | AH30: 58125.705 | AI30: 0.1055215 | AJ30: 交易手续费 | AK30: 50694.392 | AL30: 0.12118092 | AM30: 交易手续费 | AN30: 72913.867 | AO30: 0.11711892 | AP30: 交易手续费 | AQ30: 140825.34 | AR30: 0.11499947 | AS30: 交易手续费 | AT30: 34246.027 | AU30: 0.11760641 | AV30: 交易手续费 | AW30: 27582.212 | AX30: 0.12085246 | AY30: 交易手续费 | AZ30: 32226.78 | BA30: 0.11878872 | BB30: 交易手续费 | BC30: 46581.639 | BD30: 0.1135467
A31: 平台其他支出费用 | H31: 平台其他支出费用 | L31: 平台其他支出费用 | O31: 平台其他支出费用 | R31: 平台其他支出费用 | U31: 平台其他支出费用 | X31: 平台其他支出费用 | AA31: 平台其他支出费用 | AD31: 平台其他支出费用 | AG31: 平台其他支出费用 | AJ31: 平台其他支出费用 | AM31: 平台其他支出费用 | AP31: 平台其他支出费用 | AS31: 平台其他支出费用 | AV31: 平台其他支出费用 | AY31: 平台其他支出费用 | BB31: 平台其他支出费用
A32: 其他费用 | H32: 其他费用 | L32: 其他费用 | O32: 其他费用 | R32: 其他费用 | U32: 其他费用 | X32: 其他费用 | AA32: 其他费用 | AD32: 其他费用 | AG32: 其他费用 | AJ32: 其他费用 | AM32: 其他费用 | AP32: 其他费用 | AS32: 其他费用 | AV32: 其他费用 | AY32: 其他费用 | BB32: 其他费用
A33: 售后成本 | H33: 售后成本 | L33: 售后成本 | O33: 售后成本 | R33: 售后成本 | U33: 售后成本 | X33: 售后成本 | AA33: 售后成本 | AD33: 售后成本 | AG33: 售后成本 | AJ33: 售后成本 | AM33: 售后成本 | AP33: 售后成本 | AS33: 售后成本 | AV33: 售后成本 | AY33: 售后成本 | BB33: 售后成本
A34: 毛利润 | B34: =B5-B9-B13-B18-B26-B32 -> 0 | C34: =B34/B$5 -> #DIV/0! | H34: 毛利润 | I34: =I5-I9-I13-I18-I26 -> 96433.78 | J34: =I34/I5 -> 0.23339645 | L34: 毛利润 | M34: 73340.136 | N34: 0.23925848 | O34: 毛利润 | P34: 66960.28 | Q34: 0.29700112 | R34: 毛利润 | S34: 113835.73 | T34: 0.22415799 | U34: 毛利润 | V34: 75060.557 | W34: 0.25059775 | X34: 毛利润 | Y34: 91174.316 | Z34: 0.27478733 | AA34: 毛利润 | AB34: 128166.46 | AC34: 0.25947434 | AD34: 毛利润 | AE34: 75240.896 | AF34: 0.22478908 | AG34: 毛利润 | AH34: 130261.34 | AI34: 0.23647664 | AJ34: 毛利润 | AK34: 90626.079 | AL34: 0.21663444 | AM34: 毛利润 | AN34: 184560.65 | AO34: 0.29645312 | AP34: 毛利润 | AQ34: 325748.66 | AR34: 0.26600982 | AS34: 毛利润 | AT34: 48767.38 | AU34: 0.16747509 | AV34: 毛利润 | AW34: 33781.892 | AX34: 0.14801659 | AY34: 毛利润 | AZ34: 49688.772 | BA34: 0.18315407 | BB34: 毛利润 | BC34: 76069.187 | BD34: 0.18542511
A35: 毛利率 | B35: =B34/B5 -> #DIV/0! | H35: 毛利率 | I35: =I34/I5 -> 0.23339645 | L35: 毛利率 | M35: 0.23925848 | O35: 毛利率 | P35: 0.29700112 | R35: 毛利率 | S35: 0.22415799 | U35: 毛利率 | V35: 0.25059775 | X35: 毛利率 | Y35: 0.27478733 | AA35: 毛利率 | AB35: 0.25947434 | AD35: 毛利率 | AE35: 0.22478908 | AG35: 毛利率 | AH35: 0.23647664 | AJ35: 毛利率 | AK35: 0.21663444 | AM35: 毛利率 | AN35: 0.29645312 | AP35: 毛利率 | AQ35: 0.26600982 | AS35: 毛利率 | AT35: 0.16747509 | AV35: 毛利率 | AW35: 0.14801659 | AY35: 毛利率 | AZ35: 0.18315407 | BB35: 毛利率 | BC35: 0.18542511

Sheet 收入成本汇总表-最终
A1: Piscifun-SMT-201705 | E1: =SUBTOTAL(9,E3:E1048576) -> 0 | F1: =SUBTOTAL(9,F3:F1048576) -> 0 | G1: =SUBTOTAL(9,G3:G1048576) -> 0 | H1: =SUBTOTAL(9,H3:H1048576) -> 0 | I1: =SUBTOTAL(9,I3:I1048576) -> 0 | J1: =SUBTOTAL(9,J3:J1048576) -> 0 | K1: =SUBTOTAL(9,K3:K1048576) -> 0 | L1: =SUBTOTAL(9,L3:L1048576) -> 0 | M1: =SUBTOTAL(9,M3:M1048576) -> 0 | N1: SMT不涉及 | O1: =SUBTOTAL(9,O3:O1048576) -> 0 | P1: =SUBTOTAL(9,P3:P1048576) -> 0 | Q1: =SUBTOTAL(9,Q3:Q1048576) -> 0 | R1: =SUBTOTAL(9,R3:R1048576) -> 0 | S1: =SUBTOTAL(9,S3:S1048576) -> 0 | T1: =SUBTOTAL(9,T3:T1048576) -> 0 | U1: =SUBTOTAL(9,U3:U1048576) -> 0 | V1: =SUBTOTAL(9,V3:V1048576) -> 0 | ... X1: =SUBTOTAL(9,X3:X1048576) -> 0
A2: SKU类型 | B2: 匹配SKU | C2: 国家 | D2: sku&国家 | E2: 销售收入 | F2: 订单金额（人民币） | G2: 销售数量 | H2: 收入占比 | I2: 金币费（促销折扣）(人民币+汇率) | J2: 退款(人民币+汇率) | K2: 其他收入（人民币） | L2: 采购总成本(人民币) | M2: 头程总成本（人民币） | N2: 关税 | O2: 尾程物流费用 | P2: 报关费 | Q2: 尾程运输费用合计(人民币) | R2: 仓租(人民币) | S2: 交易手续费佣金11.5%（历史8%） | T2: 联盟佣金扣佣(人民币) | U2: 直通车(人民币) | V2: 保险费1% | W2: 营销技术服务费(人民币) | X2: 营销智投服务费(人民币)
A3: {=IFERROR(_xlfn.VSTACK(_xlfn._xlws.FILTER('收入成本汇总表-订单'!A3:X1048576,'收入成本汇总表-订单'!A3:A1048576<>""),_xlfn._xlws.FILTER('收入成本汇总表-退款'!A3:X1048576,'收入成本汇总表-退款'!A3:A1048576<>"")),"")} -> 26年月订单 | C3: 美国 | F3: 0 | G3: 0 | I3: 0 | J3: 0 | L3: 0 | N3: 0 | Q3: 0 | S3: 0 | T3: 0 | V3: 0
A4: 26年月退款 | C4: 美国 | E4: 0 | F4: 0 | G4: 0 | H4: 0 | I4: 0 | J4: 0 | K4: 0 | L4: 0 | M4: 0 | N4: 0 | O4: 0 | P4: 0 | Q4: 0 | R4: 0 | S4: 0 | T4: 0 | U4: 0 | V4: 0 | W4: 0 | X4: 0

Sheet 收入成本汇总表-订单
A1: Piscifun-SMT-201705 | E1: =SUBTOTAL(9,E3:E9999) -> #DIV/0! | F1: =SUBTOTAL(9,F3:F9999) -> 0 | G1: =SUBTOTAL(9,G3:G9999) -> 0 | H1: =SUBTOTAL(9,H3:H9999) -> #DIV/0! | I1: =SUBTOTAL(9,I3:I9999) -> 0 | J1: =SUBTOTAL(9,J3:J9999) -> 0 | K1: =平台激励!C2 -> 0 | L1: =SUBTOTAL(9,L3:L9999) -> 0 | M1: =头程费用!T1 -> 0 | N1: SMT不涉及 | O1: =SUBTOTAL(9,O3:O9999) -> #DIV/0! | P1: ='物流-计费明细-报关&仓租'!G1 -> 0 | Q1: =SUBTOTAL(9,Q3:Q9999) -> 0 | R1: ='物流-计费明细-报关&仓租'!E1 -> 0 | S1: =SUBTOTAL(9,S3:S9999) -> 0 | T1: =SUBTOTAL(9,T3:T9999) -> 0 | U1: =直通车!E1-直通车!F1 -> 0 | V1: =SUBTOTAL(9,V3:V9999) -> 0 | W1: =-营销技术服务费!E1 -> #VALUE! | X1: =-营销智投服务费!E1 -> #VALUE!
A2: SKU类型 | B2: 匹配SKU | C2: 国家 | D2: sku&国家 | E2: 销售收入 | F2: 订单金额（人民币） | G2: 销售数量 | H2: 收入占比 | I2: 金币费（促销折扣）(人民币+汇率) | J2: 退款(人民币+汇率) | K2: 其他收入（人民币） | L2: 采购总成本(人民币) | M2: 头程总成本（人民币） | N2: 关税 | O2: 尾程物流费用 | P2: 报关费 | Q2: 尾程运输费用合计(人民币) | R2: 仓租(人民币) | S2: 交易手续费佣金11.5%（历史8%） | T2: 联盟佣金扣佣(人民币) | U2: 直通车(人民币) | V2: 保险费1% | W2: 营销技术服务费(人民币) | X2: 营销智投服务费(人民币)
A3: ="26年"&MID(速卖通退款!$O$2,6,2)&"月订单" -> 26年月订单 | B3: {=_xlfn.UNIQUE(_xlfn._xlws.FILTER(速卖通收入!B2:B5000,速卖通收入!B2:B5000<>""))} -> #VALUE! | C3: 美国 | D3: =B3&C3 -> #VALUE! | E3: =F3+I3+J3+K3 -> #DIV/0! | F3: =SUMIF(速卖通收入!$B:$B,B3,速卖通收入!$G:$G) -> 0 | G3: =SUMIF(速卖通收入!$B:$B,B3,速卖通收入!$C:$C) -> 0 | H3: =F3/$F$1 -> #DIV/0! | I3: =-SUMIF(速卖通收入!$B:$B,B3,速卖通收入!$O:$O) -> 0 | K3: =$K$1*H3 -> #DIV/0! | L3: =SUMIF(速卖通收入!$B:$B,B3,速卖通收入!$H:$H) -> 0 | M3: =$M$1*H3 -> #DIV/0! | O3: =SUM(P3:Q3) -> #DIV/0! | P3: =$P$1*H3 -> #DIV/0! | Q3: =SUMIF(速卖通收入!$B:$B,B3,速卖通收入!$K:$K) -> 0 | R3: =$R$1*H3 -> #DIV/0! | S3: =F3*11.5% -> 0 | T3: =SUMIF(速卖通收入!$B:$B,B3,速卖通收入!$M:$M) -> 0 | U3: =$U$1*H3 -> #DIV/0! | W3: =$W$1*H3 -> #VALUE! | X3: =$X$1*H3 -> #VALUE!

Sheet 收入成本汇总表-退款
A1: Piscifun-SMT-201705 | E1: =SUBTOTAL(9,E3:E1000) -> 0 | F1: =SUBTOTAL(9,F3:F1000) -> 0 | G1: =SUBTOTAL(9,G3:G1000) -> 0 | H1: =SUBTOTAL(9,H3:H1000) -> 0 | I1: =SUBTOTAL(9,I3:I1000) -> 0 | J1: =SUBTOTAL(9,J3:J1000) -> 0 | L1: =SUBTOTAL(9,L3:L1000) -> 0 | N1: SMT不涉及 | O1: =SUBTOTAL(9,O3:O1000) -> 0 | P1: 0 | Q1: =SUBTOTAL(9,Q3:Q1000) -> 0 | S1: =SUBTOTAL(9,S3:S1000) -> 0 | T1: =SUBTOTAL(9,T3:T1000) -> 0 | V1: =SUBTOTAL(9,V3:V1000) -> 0
A2: SKU类型 | B2: 匹配SKU | C2: 国家 | D2: sku&国家 | E2: 销售收入 | F2: 订单金额（人民币） | G2: 销售数量 | H2: 收入占比 | I2: 金币费（促销折扣）(人民币+汇率) | J2: 退款(人民币+汇率) | K2: 其他收入（人民币） | L2: 采购总成本(人民币) | M2: 头程总成本（人民币） | N2: 关税 | O2: 尾程物流费用 | P2: 报关费 | Q2: 尾程运输费用合计(人民币) | R2: 仓租(人民币) | S2: 交易手续费佣金11.5%（历史8%） | T2: 联盟佣金扣佣(人民币) | U2: 直通车(人民币) | V2: 保险费1% | W2: 营销技术服务费(人民币) | X2: 营销智投服务费(人民币)
A3: ="26年"&MID(速卖通退款!$O$2,6,2)&"月退款" -> 26年月退款 | B3: {=_xlfn.UNIQUE(_xlfn._xlws.FILTER(速卖通退款!E2:E1000,速卖通退款!E2:E1000<>""))} -> #VALUE! | C3: 美国 | D3: =B3&C3 -> #VALUE! | E3: =F3+I3+J3+K3 -> 0 | I3: =SUMIF(速卖通退款!$E:$E,B3,速卖通退款!$U:$U) -> 0 | J3: =-SUMIF(速卖通退款!$E:$E,B3,速卖通退款!$Q:$Q) -> 0 | S3: =-SUMIF(速卖通退款!$E:$E,B3,速卖通退款!$V:$V) -> 0 | T3: =-SUMIF(速卖通退款!$E:$E,B3,速卖通退款!$S:$S) -> 0

Sheet 速卖通收入
A1: 订单号 | B1: 商品编码 | C1: 数量 | D1: 国家 | E1: SKU&国家 | F1: 订单金额（USD） | G1: 订单金额（人民币） | H1: 采购成本（人民币） | I1: 头程成本 | J1: 关税成本 | K1: 尾程费用（人民币） | L1: 联盟佣金扣佣（USD） | M1: 联盟佣金扣佣（人民币） | N1: 金币营销费（USD） | O1: 金币营销费（人民币） | P1: 备注 | Q1: =营销智投服务费!F2 -> 0

Sheet 速卖通退款
A1: 订单号 | B1: 商品ID | C1: 商品名称 | D1: SKU表述 | E1: 商品编码 | F1: 商品数量 | G1: 成交金额(USD) | H1: 已退款金额(USD) | I1: 退款来源 | J1: 交易佣金退回(USD) | K1: 联盟佣金退回(USD) | L1: Cashback出资返还(USD) | M1: 金币营销费退回(USD) | N1: 交易服务费退回(USD) | O1: 退款成功时间 | P1: 成交金额(人民币) | Q1: 已退款金额(人民币) | R1: 交易佣金退回(人民币) | S1: 联盟佣金退回(人民币) | T1: Cashback出资返还(人民币) | U1: 金币营销费退回(人民币) | V1: 交易服务费退回(人民币) | W1: =营销智投服务费!F2 -> 0
P2: =G2*$W$1 -> 0 | Q2: =H2*$W$1 -> 0 | R2: =J2*$W$1 -> 0 | S2: =K2*$W$1 -> 0 | T2: =L2*$W$1 -> 0 | U2: =M2*$W$1 -> 0 | V2: =N2*$W$1 -> 0

Sheet 头程费用
T1: =SUM(T3:T1048574) -> 0
A2: 费用行ID | B2: 物流单号 | C2: SO/提单号/快递单号 | D2: 集装箱号 | E2: 最晚出库日期 | F2: 进场日期 | G2: 实际离港日期 | H2: 实际到港日期 | I2: 海关出口日期 | J2: 易快报单据号 | K2: 费用阶段 | L2: 费用项 | M2: 物流供应商 | N2: 付款主体 | O2: 币种 | P2: 预估金额 | Q2: 已付款金额 | R2: 费用类别 | S2: 已对账 | T2: 实际金额 | U2: 对账日期 | V2: 账期名称 | W2: 结算日期类型 | X2: 付款申请单 | Y2: 截止对账日期 | Z2: 最后付款日期 | AA2: 是否对账异常 | AB2: 创建日期 | AC2: 创建人 | AD2: 更新人

Sheet 物流-计费明细-报关&仓租
B1: 仓储费_月结 | D1: 仓储费： | E1: =SUMIF(B:B,B1,H3:H1048576) -> 0 | F1: 报关费： | G1: =H1-E1 -> 0 | H1: =SUBTOTAL(9,H3:H51) -> 0
A2: 物流履约单号 | B2: 费用项 | C2: 运单号 | D2: 商家名称 | E2: 服务产品 | F2: 物流商品 | G2: 计费币种 | H2: 计费金额 | I2: 支付币种 | J2: 支付金额 | K2: 业务时间 | L2: 计费时间 | M2: 支付时间 | N2: 支付方式 | O2: 账单类型 | P2: 支付状态 | Q2: 支付流水号 | R2: 计费公式 | S2: 数字公式 | T2: 结算单ID | U2: 结算单分表ID | V2: 结算周期 | W2: 交易单号 | X2: ERP单号 | Y2: 仓cp的编码 | Z2: 仓库名称 | AA2: 起始省 | AB2: 起始市 | AC2: 起始区 | AD2: 目的省 | AE2: 目的市 | AF2: 目的区 | AG2: AE合单标 | AH2: 日均库存体积 | AI2: 商品数量总和 | AJ2: 包裹总重量(克) | AK2: 工厂店SKU总数量 | AL2: 周转天数 | AM2: 是否入仓首月 | AN2: 包材型号 | AO2: 包材数量 | AP2: 服务用户编码 | AQ2: 主单商品id | AR2: 主单商品名称 | AS2: 主单商品重量（g） | AT2: 主单商品长度（mm） | AU2: 主单商品宽度（mm） | AV2: 主单商品高度（mm） | AW2: 主单商品体积（mm3） | AX2: 批次日总结余体积 | AY2: 批次日结余数量

Sheet 联盟金币预计结算
AF14: 3月已经退出联盟
Q15: 2024年 | R15: 2025年 | S15: 2025年 | T15: 2025年 | U15: 2025年 | V15: 2025年 | W15: 2025年 | X15: 2025年 | Y15: 2025年 | Z15: 2025年 | AA15: 2025年 | AB15: 2025年 | AC15: 2025年 | AD15: 2026年 | AE15: 2026年 | AF15: 2026年
O16: 备注 | P16: 结算类型 | Q16: 12月 | R16: 1月 | S16: 2月 | T16: 3月 | U16: 4月 | V16: 5月 | W16: 6月 | X16: 7月 | Y16: 8月 | Z16: 9月 | AA16: 10月 | AB16: 11月 | AC16: 12月 | AD16: 26.1月 | AE16: 26.2月 | AF16: 26.3月
P17: 预计佣金 | Q17: 884.99 | R17: 699.14 | S17: 484.47 | T17: 1623.89 | U17: 729.66 | V17: 767.38 | W17: 1194.1 | X17: 825.26 | Y17: 1320.9 | Z17: 1121.3 | AA17: 1597.05 | AB17: 3273.29 | AC17: 774.45 | AD17: 656.12
P18: 结算佣金 | Q18: 597.32 | R18: 876.54 | S18: 865.38 | T18: 1137.19 | U18: 1189.09 | V18: 811.59 | W18: 1147.83 | X18: 775.14 | Y18: 1241.34 | Z18: 997.02 | AA18: 1450.47 | AB18: 3017.07 | AC18: 965.14 | AD18: 703.21
P19: 本月历史订单结算佣金 | R19: =R18-R20 -> 402.17 | S19: =S18-S20 -> 502.98 | T19: =T18-T20 -> -130.44 | U19: =U18-U20 -> 484.4 | V19: =V18-V20 -> 83 | W19: =W18-W20 -> -5.6069265 | X19: =X18-X20 -> -20.11 | Y19: =Y18-Y20 -> 17.26 | ... AF19: =AF18-AF20 -> 0
N20: 速卖通收入表 | O20: 联盟佣金 | P20: 本月当期订单结算佣金 | R20: 474.37 | S20: 362.4 | T20: 1267.63 | U20: 704.69 | V20: 728.59 | W20: 1153.4369 | X20: 795.25 | Y20: 1224.08 | Z20: =7609.770945/'[1]Aliexpress-mini管报'!G12 -> 1071.15 | AA20: =10975.768944/7.0968 -> 1546.58 | AB20: =22204.93079/'[1]Aliexpress-mini管报'!$G$14 -> 3134.74 | AC20: =5309.47053/'[1]Aliexpress-mini管报'!$G$15 -> 752.7 | AD20: =4378.276446/'[1]Aliexpress-mini管报'!$G$16 -> 625.62 | AE20: =5413.583538/'[1]Aliexpress-mini管报'!$G$17 -> 779.46
P21: 当期未结算订单佣金 | Q21: =Q17-Q18 -> 287.67 | R21: =R17-R20 -> 224.77 | S21: =S17-S20 -> 122.07 | T21: =T17-T20 -> 356.26 | U21: =U17-U20 -> 24.97 | V21: =V17-V20 -> 38.79 | W21: =W17-W20 -> 40.663073 | X21: =X17-X20 -> 30.01 | Y21: =Y17-Y20 -> 96.82 | ... AF21: =AF17-AF20 -> 0

Sheet 平台激励
B1: ="26年"&MID(速卖通退款!$O$2,5,2)&"月激励(USD)" -> 26年月激励(USD) | C1: =SUBSTITUTE(B1,"USD","人民币") -> 26年月激励(人民币) | D1: =营销智投服务费!F2 -> 0
C2: =B2*D1 -> 0

Sheet 营销技术服务费
D1: =SUM(D3:D531) -> #VALUE! | E1: =SUM(E3:E531) -> #VALUE!
A2: 结算时间 | B2: 费用项 | C2: 金额 | D2: 金额(USD) | E2: 金额(RMB) | F2: =营销智投服务费!F2 -> 0
D3: =IF(LEFT(C3,1)="U",VALUE(MID(C3,FIND("$",C3),99)),-VALUE(MID(C3,FIND("$",C3),99))) -> #VALUE! | E3: =D3*$F$2 -> #VALUE!

Sheet 营销智投服务费
D1: {=SUM(D3:D408)} -> #VALUE! | E1: {=SUM(E3:E408)} -> #VALUE!
A2: 结算时间 | B2: 费用项 | C2: 金额 | D2: 金额(USD) | E2: 金额(RMB)
D3: =IF(LEFT(C3,1)="U",VALUE(MID(C3,FIND("$",C3),99)),-VALUE(MID(C3,FIND("$",C3),99))) -> #VALUE! | E3: =D3*$F$2 -> #VALUE!

Sheet 直通车
E1: =SUBTOTAL(9,E3:E1000) -> 0 | F1: =SUBTOTAL(9,F3:F1000) -> 0
A2: 日期 | B2: 支出 | C2: 收入 | D2: 类型 | E2: 支出(人民币) | F2: 收入(人民币)
E3: =VALUE(B3) -> 0 | F3: =VALUE(C3) -> 0
